simple_spider_tools/__init__.py
simple_spider_tools/date.py
simple_spider_tools/decorator.py
simple_spider_tool17-0.17.dist-info/METADATA
simple_spider_tool17-0.17.dist-info/WHEEL
simple_spider_tool17-0.17.dist-info/licenses/LICENSE
simple_spider_tool17-0.17.dist-info/RECORD
