Metadata-Version: 2.1
Name: simple-spider-tool17
Version: 0.17
Summary: simple-spider-tool 0.0.18及后续版本兼容之前版本使用的可选扩展包
Author-email: xingc <xingcys@gmail.com>
License-Expression: MIT
License-File: LICENSE
Keywords: simple-spider-tool
Classifier: License :: OSI Approved :: MIT License
Classifier: Operating System :: OS Independent
Classifier: Programming Language :: Python :: 3
Classifier: Programming Language :: Python :: 3.5
Classifier: Programming Language :: Python :: 3.6
Classifier: Programming Language :: Python :: 3.7
Classifier: Programming Language :: Python :: 3.8
Requires-Python: >=3.5
